testingbotclient.py
testingbotclient-0.1.2.dist-info/LICENSE.txt
testingbotclient-0.1.2.dist-info/METADATA
testingbotclient-0.1.2.dist-info/WHEEL
testingbotclient-0.1.2.dist-info/top_level.txt
testingbotclient-0.1.2.dist-info/RECORD
